azure/__init__.py
azure/cli/__init__.py
azure/cli/command_modules/__init__.py
azure/cli/command_modules/consumption/__init__.py
azure/cli/command_modules/consumption/_client_factory.py
azure/cli/command_modules/consumption/_exception_handler.py
azure/cli/command_modules/consumption/_help.py
azure/cli/command_modules/consumption/_params.py
azure/cli/command_modules/consumption/_transformers.py
azure/cli/command_modules/consumption/_validators.py
azure/cli/command_modules/consumption/commands.py
azure/cli/command_modules/consumption/custom.py
azure_cli_consumption-0.4.4.dist-info/METADATA
azure_cli_consumption-0.4.4.dist-info/WHEEL
azure_cli_consumption-0.4.4.dist-info/top_level.txt
azure_cli_consumption-0.4.4.dist-info/RECORD
